LICENSE
MANIFEST.in
README.md
package.json
setup.py
assets/img/waternormals.jpg
assets/models/beech.gltf
assets/models/lime.gltf
assets/models/mountains.glb
assets/models/spruce.gltf
forest_threejs/ForestThreejs.py
forest_threejs/__init__.py
forest_threejs/_imports_.py
forest_threejs/forest_threejs.min.js
forest_threejs/forest_threejs.min.js.map
forest_threejs/metadata.json
forest_threejs/package-info.json
forest_threejs.egg-info/PKG-INFO
forest_threejs.egg-info/SOURCES.txt
forest_threejs.egg-info/dependency_links.txt
forest_threejs.egg-info/top_level.txt