Metadata-Version: 2.1
Name: forest-threejs
Version: 0.0.2
Summary: Threejs rendering of a foggy forest built into a dash component
Home-page: UNKNOWN
Author: Ben Cannell <bean.can.design@gmail.com>
License: GPL-3.0
Platform: UNKNOWN
Classifier: Framework :: Dash
License-File: LICENSE
